asw_mather/__init__.py
asw_mather/circle.py
asw_mather/types.py
asw_mather/util.py
asw_mather/version.py
asw_mather-0.1.0.dist-info/licenses/LICENSE
asw_mather-0.1.0.dist-info/METADATA
asw_mather-0.1.0.dist-info/WHEEL
asw_mather-0.1.0.dist-info/top_level.txt
asw_mather-0.1.0.dist-info/RECORD
